odoo8_addon_website_product_show_uom-8.0.1.0.0.99.dev5-py2.7-nspkg.pth
odoo8_addon_website_product_show_uom-8.0.1.0.0.99.dev5.dist-info/DESCRIPTION.rst
odoo8_addon_website_product_show_uom-8.0.1.0.0.99.dev5.dist-info/METADATA
odoo8_addon_website_product_show_uom-8.0.1.0.0.99.dev5.dist-info/RECORD
odoo8_addon_website_product_show_uom-8.0.1.0.0.99.dev5.dist-info/WHEEL
odoo8_addon_website_product_show_uom-8.0.1.0.0.99.dev5.dist-info/metadata.json
odoo8_addon_website_product_show_uom-8.0.1.0.0.99.dev5.dist-info/namespace_packages.txt
odoo8_addon_website_product_show_uom-8.0.1.0.0.99.dev5.dist-info/top_level.txt
odoo_addons/website_product_show_uom/README.rst
odoo_addons/website_product_show_uom/__init__.py
odoo_addons/website_product_show_uom/__openerp__.py
odoo_addons/website_product_show_uom/demo/website_settings.yml
odoo_addons/website_product_show_uom/i18n/de.po
odoo_addons/website_product_show_uom/i18n/es.po
odoo_addons/website_product_show_uom/i18n/fr.po
odoo_addons/website_product_show_uom/i18n/it.po
odoo_addons/website_product_show_uom/i18n/pt_BR.po
odoo_addons/website_product_show_uom/i18n/sl.po
odoo_addons/website_product_show_uom/i18n/tr.po
odoo_addons/website_product_show_uom/security/ir.model.access.csv
odoo_addons/website_product_show_uom/static/description/icon.png
odoo_addons/website_product_show_uom/static/src/js/website_test_uom.js
odoo_addons/website_product_show_uom/tests/__init__.py
odoo_addons/website_product_show_uom/tests/test_website_uom.py
odoo_addons/website_product_show_uom/views/assets.xml
odoo_addons/website_product_show_uom/views/website_product.xml
